alyeska/__init__.py
alyeska/compose/__init__.py
alyeska/compose/compose_sh.py
alyeska/compose/config.py
alyeska/compose/exceptions.py
alyeska/compose/validate.py
alyeska/locksmith/__init__.py
alyeska/locksmith/authmfa.py
alyeska/locksmith/redshift.py
alyeska/logging/__init__.py
alyeska/redpandas/__init__.py
alyeska/redpandas/exceptions.py
alyeska/sqlagent/__init__.py
alyeska-0.3.0a1.dist-info/LICENSE
alyeska-0.3.0a1.dist-info/METADATA
alyeska-0.3.0a1.dist-info/WHEEL
alyeska-0.3.0a1.dist-info/entry_points.txt
alyeska-0.3.0a1.dist-info/top_level.txt
alyeska-0.3.0a1.dist-info/RECORD
