Metadata-Version: 2.1
Name: alyeska
Version: 0.3.0a1
Summary: Alyeska /al-ee-EHS-kah/ n. A Data Pipeline Toolkit
Home-page: https://github.com/Dynatrace/alyeska
Author: Nick Vogt
Author-email: nick.vogt@dynatrace.com
License: UNKNOWN
Platform: UNKNOWN
Classifier: Programming Language :: Python :: 3.6
Classifier: Programming Language :: Python :: 3.7
Classifier: Programming Language :: Python :: 3.8
Classifier: Development Status :: 3 - Alpha
Classifier: License :: OSI Approved :: Apache Software License
Classifier: Operating System :: OS Independent
Requires-Dist: boto3 (>=1.9.197)
Requires-Dist: packaging (>=19.2)
Requires-Dist: pandas (>=0.25.0)
Requires-Dist: psycopg2-binary (>=2.8.3)
Requires-Dist: pyotp (>=2.3.0)
Requires-Dist: pytz (>=2019.1)
Requires-Dist: pyyaml (>=5.1)
